embarrassment/__init__.py
embarrassment/api.py
embarrassment/py.typed
embarrassment-0.1.0.dist-info/WHEEL
embarrassment-0.1.0.dist-info/METADATA
embarrassment-0.1.0.dist-info/RECORD
