Metadata-Version: 2.1
Name: embarrassment
Version: 0.1.0
Summary: Convenience functions to work with pandas triple dataframes 🐼🐼🐼
Home-page: https://github.com/dobraczka/embarrassment
License: MIT
Keywords: pandas,rdf,knowledge graph
Author: Daniel Obraczka
Author-email: obraczka@informatik.uni-leipzig.de
Requires-Python: >=3.8,<4.0
Classifier: Development Status :: 4 - Beta
Classifier: License :: OSI Approved :: MIT License
Classifier: Programming Language :: Python
Classifier: Programming Language :: Python :: 3
Classifier: Programming Language :: Python :: 3.8
Classifier: Programming Language :: Python :: 3.9
Classifier: Programming Language :: Python :: 3.10
Classifier: Programming Language :: Python :: 3.11
Classifier: Programming Language :: Python :: 3 :: Only
Classifier: Programming Language :: Python :: 3.10
Classifier: Programming Language :: Python :: 3.8
Classifier: Programming Language :: Python :: 3.9
Provides-Extra: docs
Requires-Dist: mkdocs (>=1.5.3,<2.0.0) ; extra == "docs"
Requires-Dist: mkdocs-gen-files (>=0.5.0,<0.6.0) ; extra == "docs"
Requires-Dist: mkdocs-literate-nav (>=0.6.1,<0.7.0) ; extra == "docs"
Requires-Dist: mkdocs-material (>=9.5.8,<10.0.0) ; extra == "docs"
Requires-Dist: mkdocs-section-index (>=0.3.8,<0.4.0) ; extra == "docs"
Requires-Dist: mkdocstrings[python] (>=0.24.0,<0.25.0) ; extra == "docs"
Requires-Dist: pandas (>=2,<3)
Project-URL: Bug Tracker, https://github.com/dobraczka/embarrassment/issues
Project-URL: Documentation, https://embarrassment.readthedocs.io
Project-URL: Repository, https://github.com/dobraczka/embarrassment
Project-URL: Source, https://github.com/dobraczka/embarrassment
